json_to_ical/__init__.py
json_to_ical/convert.py
json_to_ical/main.py
json_to_ical-2025.1.2.dist-info/licenses/LICENSE
json_to_ical-2025.1.2.dist-info/WHEEL
json_to_ical-2025.1.2.dist-info/entry_points.txt
json_to_ical-2025.1.2.dist-info/METADATA
json_to_ical-2025.1.2.dist-info/RECORD
