Metadata-Version: 2.4
Name: json-to-ical
Version: 2025.1.2
Summary: Script to convert json calendar data to ical format
Author: Ben Fitzhardinge
Author-email: Ben Fitzhardinge <ben@benjamin.dog>
License-Expression: GPL-2.0-or-later
License-File: LICENSE
Classifier: Development Status :: 4 - Beta
Classifier: Intended Audience :: Developers
Classifier: Programming Language :: Python :: 3
Classifier: Programming Language :: Python :: 3.9
Classifier: Programming Language :: Python :: 3.10
Classifier: Programming Language :: Python :: 3.11
Classifier: Programming Language :: Python :: 3.12
Classifier: Programming Language :: Python :: 3.13
Requires-Dist: ical>=4.5.4,<5.0.0 ; python_full_version == '3.9.*'
Requires-Dist: ical>=4.5.4,<8.3.0 ; python_full_version == '3.10.*'
Requires-Dist: ical>=9.0.0 ; python_full_version >= '3.11'
Maintainer: Ben Fitzhardinge
Maintainer-email: Ben Fitzhardinge <ben@benjamin.dog>
Requires-Python: >=3.9
Project-URL: Homepage, https://github.com/bendog/pyconau-ical
Project-URL: Repository, https://github.com/bendog/pyconau-ical.git
